aiolastfm/__init__.py
aiolastfm/client.py
aiolastfm/exceptions.py
aiolastfm/http.py
aiolastfm/py.typed
aiolastfm/types/http.py
aiolastfm/types/payloads.py
aiolastfm/utilities.py
LICENSE
aiolastfm-0.0.3.dist-info/LICENSE
aiolastfm-0.0.3.dist-info/WHEEL
aiolastfm-0.0.3.dist-info/METADATA
aiolastfm-0.0.3.dist-info/RECORD
